<annotation>
	<folder>train</folder>
	<filename>name127.jpg</filename>
	<path>/home/alvaro/Desktop/object_detection_demo/data/images/train/name127.jpg</path>
	<source>
		<database>Unknown</database>
	</source>
	<size>
		<width>4000</width>
		<height>2250</height>
		<depth>3</depth>
	</size>
	<segmented>0</segmented>
	<object>
		<name>ferrugem</name>
		<pose>Unspecified</pose>
		<truncated>0</truncated>
		<difficult>0</difficult>
		<bndbox>
			<xmin>3660</xmin>
			<ymin>920</ymin>
			<xmax>3785</xmax>
			<ymax>1046</ymax>
		</bndbox>
	</object>
	<object>
		<name>ferrugem</name>
		<pose>Unspecified</pose>
		<truncated>0</truncated>
		<difficult>0</difficult>
		<bndbox>
			<xmin>3305</xmin>
			<ymin>626</ymin>
			<xmax>3420</xmax>
			<ymax>740</ymax>
		</bndbox>
	</object>
	<object>
		<name>ferrugem</name>
		<pose>Unspecified</pose>
		<truncated>0</truncated>
		<difficult>0</difficult>
		<bndbox>
			<xmin>2325</xmin>
			<ymin>472</ymin>
			<xmax>2420</xmax>
			<ymax>560</ymax>
		</bndbox>
	</object>
	<object>
		<name>ferrugem</name>
		<pose>Unspecified</pose>
		<truncated>0</truncated>
		<difficult>0</difficult>
		<bndbox>
			<xmin>2951</xmin>
			<ymin>1254</ymin>
			<xmax>3105</xmax>
			<ymax>1383</ymax>
		</bndbox>
	</object>
</annotation>
